jundo/__init__.py
jundo/_version.py
jundo/undoManager.py
jundo-0.1.2.dist-info/LICENSE
jundo-0.1.2.dist-info/METADATA
jundo-0.1.2.dist-info/WHEEL
jundo-0.1.2.dist-info/top_level.txt
jundo-0.1.2.dist-info/RECORD
